LICENSE
scamadviser_client/__init__.py
scamadviser_client/base_api.py
scamadviser_client/feed_api.py
scamadviser_client/request.py
scamadviser_client/schema/__init__.py
scamadviser_client/schema/feed_params.py
scamadviser_client/schema/response.py
scamadviser_client-0.2.1.dist-info/LICENSE
scamadviser_client-0.2.1.dist-info/WHEEL
scamadviser_client-0.2.1.dist-info/METADATA
scamadviser_client-0.2.1.dist-info/RECORD
