Metadata-Version: 2.1
Name: scamadviser-client
Version: 0.2.1
Summary: A python SDK for ScamAdviser API
Home-page: https://github.com/gogolook-Inc/scamadviser_client
License: MIT
Keywords: scamadviser, sdk, api
Author: Carol H
Author-email: sheseee@gmail.com
Requires-Python: >=3.7,<4.0
Classifier: License :: OSI Approved :: MIT License
Classifier: Programming Language :: Python :: 3
Classifier: Programming Language :: Python :: 3.10
Classifier: Programming Language :: Python :: 3.7
Classifier: Programming Language :: Python :: 3.8
Classifier: Programming Language :: Python :: 3.9
Requires-Dist: pydantic (>=1.10.4,<2.0.0)
Requires-Dist: requests (>=2.28.1,<3.0.0)
Project-URL: Repository, https://github.com/gogolook-Inc/scamadviser_client
